read_env.py
read_env-1.1.0.dist-info/DESCRIPTION.rst
read_env-1.1.0.dist-info/METADATA
read_env-1.1.0.dist-info/RECORD
read_env-1.1.0.dist-info/WHEEL
read_env-1.1.0.dist-info/metadata.json
read_env-1.1.0.dist-info/top_level.txt
