Metadata-Version: 2.0
Name: read-env
Version: 1.1.0
Summary: reads .env files into os.environ
Home-page: https://github.com/sloria/read_env
Author: Steven Loria
Author-email: sloria1@gmail.com
License: MIT
Keywords: env environment variables
Platform: UNKNOWN
Classifier: Intended Audience :: Developers
Classifier: License :: OSI Approved :: MIT License
Classifier: Natural Language :: English
Classifier: Programming Language :: Python :: 2
Classifier: Programming Language :: Python :: 2.7
Classifier: Programming Language :: Python :: 3
Classifier: Programming Language :: Python :: 3.3
Classifier: Programming Language :: Python :: 3.4
Classifier: Programming Language :: Python :: 3.5
Classifier: Programming Language :: Python :: Implementation :: CPython
Classifier: Programming Language :: Python :: Implementation :: PyPy
